yq_pystand_setup/Activate.ps1
yq_pystand_setup/__main__.py
yq_pystand_setup/_version.py
yq_pystand_setup/main.py
yq_pystand_setup-0.1.3.dist-info/LICENSE
yq_pystand_setup-0.1.3.dist-info/METADATA
yq_pystand_setup-0.1.3.dist-info/WHEEL
yq_pystand_setup-0.1.3.dist-info/top_level.txt
yq_pystand_setup-0.1.3.dist-info/RECORD
